     {
    "Contacts": [
    {
      "FirstName": "Harsh",
      "LastName": "Singh",
	  "Contactno":"+919357724500"
    },
  
	{
      "FirstName": "Kisan",
      "LastName": "Network",
	  "Contactno":"+919971792703"
    },

      {
        "FirstName": "Ram",
        "LastName": "Kumar",
        "Contactno":"+919988776655"
      },

      {
        "FirstName": "Vishal",
        "LastName": "Sharma",
        "Contactno":"+91987654321"
      },

      {
        "FirstName": "Aditya",
        "LastName": "Kapoor",
        "Contactno":"+918754236856"
      },

    {
      "FirstName": "Trial1",
      "LastName": "Singh",
	  "Contactno":"+9112345678"
    },
  
  
	{
      "FirstName": "Trial2",
      "LastName": "Singh",
	  "Contactno":"+9112345678"
    },
  
  
	{
      "FirstName": "Trial3",
      "LastName": "Singh",
	  "Contactno":"+9112345678"
    },


      {
        "FirstName": "Trial4",
        "LastName": "Singh",
        "Contactno":"+9112345678"
      }




    ]
}